pandas_query_mcp/__init__.py
pandas_query_mcp/py.typed
pandas_query_mcp/server.py
pandas_query_mcp-0.1.0.dist-info/METADATA
pandas_query_mcp-0.1.0.dist-info/WHEEL
pandas_query_mcp-0.1.0.dist-info/entry_points.txt
pandas_query_mcp-0.1.0.dist-info/RECORD
